{
    "created_time": "2023-06-27T01:03:18Z",
    "files": [
        {
            "attachment_folder": "",
            "created_time": "2023-06-06T14:48:20Z",
            "id": "53",
            "modified_time": "2023-06-06T14:48:20Z",
            "name": "computer_system.png",
            "signature": "207324052408116",
            "tags": [
            ]
        },
        {
            "attachment_folder": "",
            "created_time": "2023-06-09T14:02:54Z",
            "id": "57",
            "modified_time": "2023-06-09T14:02:54Z",
            "name": "early_von_neumann_machine_structure.png",
            "signature": "5546498803277967630",
            "tags": [
            ]
        },
        {
            "attachment_folder": "",
            "created_time": "2023-06-09T14:02:51Z",
            "id": "56",
            "modified_time": "2023-06-09T14:02:51Z",
            "name": "modern_computer_structure.png",
            "signature": "784285914976432395",
            "tags": [
            ]
        },
        {
            "attachment_folder": "",
            "created_time": "2023-06-09T14:02:48Z",
            "id": "55",
            "modified_time": "2023-06-09T14:02:48Z",
            "name": "nth_power_of_2.png",
            "signature": "207324052664584",
            "tags": [
            ]
        },
        {
            "attachment_folder": "",
            "created_time": "2023-06-09T14:02:57Z",
            "id": "58",
            "modified_time": "2023-06-09T14:02:57Z",
            "name": "cpu_performance_metrics.png",
            "signature": "8223662518577606929",
            "tags": [
            ]
        },
        {
            "attachment_folder": "",
            "created_time": "2023-06-11T06:27:17Z",
            "id": "59",
            "modified_time": "2023-06-11T06:27:17Z",
            "name": "binary_to_octal_and_hexadecimal.png",
            "signature": "207324052810053",
            "tags": [
            ]
        },
        {
            "attachment_folder": "",
            "created_time": "2023-06-27T01:06:47Z",
            "id": "65",
            "modified_time": "2023-06-27T01:06:47Z",
            "name": "unsigned_int_representation_in_hardware.png",
            "signature": "5546498803279476263",
            "tags": [
            ]
        },
        {
            "attachment_folder": "",
            "created_time": "2023-06-11T08:50:50Z",
            "id": "60",
            "modified_time": "2023-06-11T08:50:50Z",
            "name": "storage_hierarchical_structure_pyramid.png",
            "signature": "784285914976586474",
            "tags": [
            ]
        },
        {
            "attachment_folder": "",
            "created_time": "2023-06-11T13:02:27Z",
            "id": "61",
            "modified_time": "2023-06-11T13:02:27Z",
            "name": "storage_hierarchical_structure.png",
            "signature": "207324052833763",
            "tags": [
            ]
        },
        {
            "attachment_folder": "",
            "created_time": "2023-06-28T08:26:02Z",
            "id": "77",
            "modified_time": "2023-06-28T08:26:02Z",
            "name": "convert_integer_part_1.png",
            "signature": "207324054285978",
            "tags": [
            ]
        },
        {
            "attachment_folder": "",
            "created_time": "2023-06-28T08:27:44Z",
            "id": "78",
            "modified_time": "2023-06-28T08:27:44Z",
            "name": "convert_integer_part_2.png",
            "signature": "784285914978053888",
            "tags": [
            ]
        },
        {
            "attachment_folder": "",
            "created_time": "2023-07-06T07:40:25Z",
            "id": "82",
            "modified_time": "2023-07-06T07:40:25Z",
            "name": "true_form_representation.png",
            "signature": "207324054974441",
            "tags": [
            ]
        },
        {
            "attachment_folder": "",
            "created_time": "2023-07-08T02:38:10Z",
            "id": "83",
            "modified_time": "2023-07-08T02:38:10Z",
            "name": "convert_fractional_part.png",
            "signature": "207324055129106",
            "tags": [
            ]
        },
        {
            "attachment_folder": "",
            "created_time": "2023-07-09T06:46:06Z",
            "id": "85",
            "modified_time": "2023-07-09T06:46:06Z",
            "name": "get_complement_normal.png",
            "signature": "207324055230382",
            "tags": [
            ]
        }
    ],
    "folders": [
    ],
    "id": "64",
    "modified_time": "2023-06-27T01:03:18Z",
    "signature": "784285914977940822",
    "version": 3
}
